looker_powerpoint/__init__.py
looker_powerpoint/cli.py
looker_powerpoint/looker.py
looker_powerpoint/models.py
looker_powerpoint/tools/__init__.py
looker_powerpoint/tools/find_alt_text.py
looker_powerpoint/tools/pptx_text_handler.py
looker_powerpoint/tools/url_to_hyperlink.py
looker_powerpoint-0.6.0.dist-info/METADATA
looker_powerpoint-0.6.0.dist-info/WHEEL
looker_powerpoint-0.6.0.dist-info/entry_points.txt
looker_powerpoint-0.6.0.dist-info/licenses/LICENSE
looker_powerpoint-0.6.0.dist-info/RECORD
