Metadata-Version: 2.4
Name: looker_powerpoint
Version: 0.6.0
Summary: Add your description here
License-File: LICENSE
Requires-Python: >=3.12
Requires-Dist: black>=25.1.0
Requires-Dist: deepdiff>=8.6.1
Requires-Dist: jinja2>=3.1.6
Requires-Dist: looker-sdk>=25.10.0
Requires-Dist: pandas>=2.3.1
Requires-Dist: pydantic>=2.11.7
Requires-Dist: python-dotenv>=1.1.1
Requires-Dist: python-pptx>=1.0.2
Requires-Dist: pyyaml>=6.0.2
Requires-Dist: rich-argparse>=1.7.1
Requires-Dist: rich>=14.1.0
Requires-Dist: tenacity>=9.1.2
